django_super_svgs/management/commands/create_snippets.py
django_super_svgs/static/django_super_svgs/css/main.css
django_super_svgs/static/django_super_svgs/css/style.css
django_super_svgs/static/django_super_svgs/css/style.css.map
django_super_svgs/static/django_super_svgs/fonts/poppins-regular-webfont.woff
django_super_svgs/static/django_super_svgs/fonts/poppins-regular-webfont.woff2
django_super_svgs/static/django_super_svgs/img/favicon.ico
django_super_svgs/static/django_super_svgs/js/app.js
django_super_svgs/templates/django_super_svgs/index.html
django_super_svgs/templatetags/base.py
django_super_svgs/templatetags/super_svgs.py
django_super_svgs/templatetags/svgs/__init__.py
django_super_svgs/templatetags/svgs/bootstrap.py
django_super_svgs/templatetags/svgs/dripicons.py
django_super_svgs/templatetags/svgs/hero_outline.py
django_super_svgs/templatetags/svgs/hero_solid.py
django_super_svgs/templatetags/svgs/material.py
django_super_svgs/tests/__init__.py
django_super_svgs/tests/test_snippets.py
django_super_svgs/tests/test_templates.py
django_super_svgs/tests/test_views.py
django_super_svgs/urls.py
django_super_svgs/views.py
django_super_svgs-0.3.2.dist-info/LICENSE
django_super_svgs-0.3.2.dist-info/METADATA
django_super_svgs-0.3.2.dist-info/WHEEL
django_super_svgs-0.3.2.dist-info/RECORD
